ssht/__init__.py
ssht/plugins.py
ssht/ssht.py
ssht-2.0.2.dist-info/LICENSE
ssht-2.0.2.dist-info/METADATA
ssht-2.0.2.dist-info/WHEEL
ssht-2.0.2.dist-info/entry_points.txt
ssht-2.0.2.dist-info/RECORD
