Metadata-Version: 2.3
Name: ssht
Version: 2.0.2
Summary: SSH client wrapper for easily connecting to hosts
Author: Henk Kraal
Author-email: hkraal@users.noreply.github.com
Requires-Python: >3.9.1,<3.14
Classifier: Development Status :: 4 - Beta
Classifier: Environment :: Console
Classifier: Intended Audience :: System Administrators
Classifier: License :: OSI Approved :: MIT License
Classifier: Programming Language :: Python :: 3
Classifier: Programming Language :: Python :: 3.10
Classifier: Programming Language :: Python :: 3.11
Classifier: Programming Language :: Python :: 3.12
Classifier: Programming Language :: Python :: 3.13
Classifier: Programming Language :: Python :: 3.9
Classifier: Topic :: System :: Shells
Classifier: Topic :: Utilities
Requires-Dist: mysql-connector (>=2.2.9,<3.0.0)
Requires-Dist: requests (>=2.31.0,<3.0.0)
